rcpchgrowth_python_cli/__init__.py
rcpchgrowth_python_cli/__main__.py
rcpchgrowth_python_cli-1.2.0.dist-info/LICENSE
rcpchgrowth_python_cli-1.2.0.dist-info/METADATA
rcpchgrowth_python_cli-1.2.0.dist-info/WHEEL
rcpchgrowth_python_cli-1.2.0.dist-info/entry_points.txt
rcpchgrowth_python_cli-1.2.0.dist-info/top_level.txt
rcpchgrowth_python_cli-1.2.0.dist-info/RECORD
