Metadata-Version: 2.1
Name: rcpchgrowth-python-cli
Version: 1.2.0
Summary: Command Line Interface for RCPCHGrowth.
Home-page: https://github.com/rcpch/rcpchgrowth-python-cli
Author: Simon Chapman, Marcus Baw
Author-email: eatyourpeasapps@gmail.com
Keywords: RCPCHGrowth UK-WHO Down Turner Centile
Classifier: Programming Language :: Python :: 3
Classifier: License :: OSI Approved :: GNU Affero General Public License v3 or later (AGPLv3+)
Classifier: Operating System :: OS Independent
License-File: LICENSE
Requires-Dist: click
Requires-Dist: pyfiglet
Requires-Dist: rcpchgrowth
Requires-Dist: scipy
Requires-Dist: bump2version
